<database>
 <name>dummy</name>
 <create>false</create>
 <overwrite>false</overwrite>

 <table>
  <name>category</name>
  <declaration>
   <field>
    <name>category_id</name>
    <autoincrement>true</autoincrement>
    <type>integer</type>
    <unsigned>true</unsigned>
    <notnull>true</notnull>
    <length>10</length>
   </field>
   <field>
    <name>category_created</name>
    <type>integer</type>
    <unsigned>true</unsigned>
    <notnull>true</notnull>
    <length>10</length>
   </field>
   <field>
    <name>category_updated</name>
    <type>integer</type>
    <unsigned>true</unsigned>
    <notnull>true</notnull>
    <length>10</length>
   </field>
   <field>
    <name>category_name</name>
    <type>text</type>
    <notnull>true</notnull>
    <length>255</length>
   </field>
   <field>
    <name>category_description</name>
    <type>clob</type>
    <notnull>true</notnull>
   </field>
   <field>
    <name>category_parent</name>
    <type>integer</type>
    <unsigned>true</unsigned>
    <notnull>false</notnull>
    <length>10</length>
   </field>
   <field>
    <name>category_node_count</name>
    <type>integer</type>
    <unsigned>true</unsigned>
    <notnull>true</notnull>
    <length>10</length>
   </field>
   <field>
    <name>category_node_last</name>
    <type>integer</type>
    <unsigned>true</unsigned>
    <notnull>true</notnull>
    <length>10</length>
   </field>
   <field>
    <name>category_node_lasttime</name>
    <type>integer</type>
    <unsigned>true</unsigned>
    <notnull>true</notnull>
    <length>10</length>
   </field>
   <index>
    <name>PRIMARY</name>
    <primary>true</primary>
    <field>
     <name>category_id</name>
     <sorting>ascending</sorting>
    </field>
   </index>
  </declaration>
  <initialization>
  </initialization>
 </table>

 <table>
  <name>node</name>
  <declaration>
   <field>
    <name>node_id</name>
    <autoincrement>true</autoincrement>
    <type>integer</type>
    <unsigned>true</unsigned>
    <notnull>true</notnull>
    <length>10</length>
   </field>
   <field>
    <name>node_created</name>
    <type>integer</type>
    <unsigned>true</unsigned>
    <notnull>true</notnull>
    <length>10</length>
   </field>
   <field>
    <name>node_updated</name>
    <type>integer</type>
    <unsigned>true</unsigned>
    <notnull>true</notnull>
    <length>10</length>
   </field>
   <field>
    <name>node_title</name>
    <type>text</type>
    <notnull>true</notnull>
    <length>255</length>
   </field>
   <field>
    <name>node_source</name>
    <type>text</type>
    <notnull>true</notnull>
    <length>255</length>
   </field>
   <field>
    <name>node_source_title</name>
    <type>text</type>
    <notnull>true</notnull>
    <length>255</length>
   </field>
   <field>
    <name>node_content_syntax</name>
    <type>text</type>
    <notnull>true</notnull>
    <length>255</length>
   </field>
   <field>
    <name>node_body</name>
    <type>clob</type>
    <notnull>true</notnull>
   </field>
   <field>
    <name>node_body_html</name>
    <type>clob</type>
    <notnull>true</notnull>
   </field>
   <field>
    <name>node_teaser</name>
    <type>clob</type>
    <notnull>true</notnull>
   </field>
   <field>
    <name>node_teaser_html</name>
    <type>clob</type>
    <notnull>true</notnull>
   </field>
   <field>
    <name>node_published</name>
    <type>integer</type>
    <unsigned>true</unsigned>
    <notnull>true</notnull>
    <length>10</length>
   </field>
   <field>
    <name>node_allow_comments</name>
    <type>integer</type>
    <unsigned>true</unsigned>
    <notnull>true</notnull>
    <length>1</length>
    <default>1</default>
   </field>
   <field>
    <name>node_allow_trackbacks</name>
    <type>integer</type>
    <unsigned>true</unsigned>
    <notnull>true</notnull>
    <length>1</length>
    <default>1</default>
   </field>
   <field>
    <name>node_allow_edit</name>
    <type>integer</type>
    <unsigned>true</unsigned>
    <notnull>true</notnull>
    <length>1</length>
    <default>1</default>
   </field>
   <field>
    <name>node_status</name>
    <type>integer</type>
    <unsigned>true</unsigned>
    <notnull>true</notnull>
    <length>1</length>
   </field>
   <field>
    <name>node_hidden</name>
    <type>integer</type>
    <unsigned>true</unsigned>
    <notnull>true</notnull>
    <length>1</length>
   </field>
   <field>
    <name>node_priority</name>
    <type>integer</type>
    <unsigned>true</unsigned>
    <notnull>true</notnull>
    <length>5</length>
   </field>
   <field>
    <name>node_views</name>
    <type>integer</type>
    <unsigned>true</unsigned>
    <notnull>true</notnull>
    <length>10</length>
   </field>
   <field>
    <name>node_category_id</name>
    <type>integer</type>
    <unsigned>true</unsigned>
    <notnull>false</notnull>
    <length>10</length>
   </field>
   <field>
    <name>node_userid</name>
    <type>text</type>
    <notnull>true</notnull>
    <length>255</length>
   </field>
   <field>
    <name>node_comment_count</name>
    <type>integer</type>
    <unsigned>true</unsigned>
    <notnull>true</notnull>
    <length>10</length>
   </field>
   <field>
    <name>node_comment_last</name>
    <type>integer</type>
    <unsigned>true</unsigned>
    <notnull>true</notnull>
    <length>10</length>
   </field>
   <field>
    <name>node_comment_lasttime</name>
    <type>integer</type>
    <unsigned>true</unsigned>
    <notnull>true</notnull>
    <length>10</length>
   </field>
   <field>
    <name>node_trackback_count</name>
    <type>integer</type>
    <unsigned>true</unsigned>
    <notnull>true</notnull>
    <length>10</length>
   </field>
   <field>
    <name>node_trackback_last</name>
    <type>integer</type>
    <unsigned>true</unsigned>
    <notnull>true</notnull>
    <length>10</length>
   </field>
   <field>
    <name>node_trackback_lasttime</name>
    <type>integer</type>
    <unsigned>true</unsigned>
    <notnull>true</notnull>
    <length>10</length>
   </field>
   <field>
    <name>node_vote_count</name>
    <type>integer</type>
    <unsigned>true</unsigned>
    <notnull>true</notnull>
    <length>10</length>
   </field>
   <field>
    <name>node_vote_last</name>
    <type>integer</type>
    <unsigned>true</unsigned>
    <notnull>true</notnull>
    <length>10</length>
   </field>
   <field>
    <name>node_vote_lasttime</name>
    <type>integer</type>
    <unsigned>true</unsigned>
    <notnull>true</notnull>
    <length>10</length>
   </field>
   <field>
    <name>node_view_count</name>
    <type>integer</type>
    <unsigned>true</unsigned>
    <notnull>true</notnull>
    <length>10</length>
   </field>
   <field>
    <name>node_view_last</name>
    <type>integer</type>
    <unsigned>true</unsigned>
    <notnull>true</notnull>
    <length>10</length>
   </field>
   <field>
    <name>node_view_lasttime</name>
    <type>integer</type>
    <unsigned>true</unsigned>
    <notnull>true</notnull>
    <length>10</length>
   </field>
   <index>
    <name>PRIMARY</name>
    <primary>true</primary>
    <field>
     <name>node_id</name>
     <sorting>ascending</sorting>
    </field>
   </index>
   <index>
    <name>node_category</name>
    <field>
     <name>node_category_id</name>
    </field>
   </index>
   <index>
    <name>node_priority</name>
    <field>
     <name>node_priority</name>
     <sorting>descending</sorting>
    </field>
   </index>
   <index>
    <name>node_status_hidden</name>
    <field>
     <name>node_status</name>
    </field>
    <field>
     <name>node_hidden</name>
    </field>
   </index>
  </declaration>
  <initialization>
  </initialization>
 </table>

 <table>
  <name>comment</name>
  <declaration>
   <field>
    <name>comment_id</name>
    <autoincrement>true</autoincrement>
    <type>integer</type>
    <unsigned>true</unsigned>
    <notnull>true</notnull>
    <length>10</length>
   </field>
   <field>
    <name>comment_created</name>
    <type>integer</type>
    <unsigned>true</unsigned>
    <notnull>true</notnull>
    <length>10</length>
   </field>
   <field>
    <name>comment_updated</name>
    <type>integer</type>
    <unsigned>true</unsigned>
    <notnull>true</notnull>
    <length>10</length>
   </field>
   <field>
    <name>comment_title</name>
    <type>text</type>
    <notnull>true</notnull>
    <length>255</length>
   </field>
   <field>
    <name>comment_content_syntax</name>
    <type>text</type>
    <notnull>true</notnull>
    <length>255</length>
   </field>
   <field>
    <name>comment_body</name>
    <type>clob</type>
    <notnull>true</notnull>
   </field>
   <field>
    <name>comment_body_html</name>
    <type>clob</type>
    <notnull>true</notnull>
   </field>
   <field>
    <name>comment_allow_edit</name>
    <type>integer</type>
    <unsigned>true</unsigned>
    <notnull>true</notnull>
    <length>1</length>
    <default>1</default>
   </field>
   <field>
    <name>comment_node_id</name>
    <type>integer</type>
    <unsigned>true</unsigned>
    <notnull>false</notnull>
    <length>10</length>
   </field>
   <field>
    <name>comment_parent</name>
    <type>integer</type>
    <unsigned>true</unsigned>
    <notnull>false</notnull>
    <length>10</length>
   </field>
   <field>
    <name>comment_userid</name>
    <type>text</type>
    <notnull>true</notnull>
    <length>255</length>
   </field>
   <index>
    <name>PRIMARY</name>
    <primary>true</primary>
    <field>
     <name>comment_id</name>
     <sorting>ascending</sorting>
    </field>
   </index>
   <index>
    <name>comment_node</name>
    <field>
     <name>comment_node_id</name>
    </field>
   </index>
  </declaration>
  <initialization>
  </initialization>
 </table>

 <table>
  <name>trackback</name>
  <declaration>
   <field>
    <name>trackback_id</name>
    <autoincrement>true</autoincrement>
    <type>integer</type>
    <unsigned>true</unsigned>
    <notnull>true</notnull>
    <length>10</length>
   </field>
   <field>
    <name>trackback_created</name>
    <type>integer</type>
    <unsigned>true</unsigned>
    <notnull>true</notnull>
    <length>10</length>
   </field>
   <field>
    <name>trackback_updated</name>
    <type>integer</type>
    <unsigned>true</unsigned>
    <notnull>true</notnull>
    <length>10</length>
   </field>
   <field>
    <name>trackback_title</name>
    <type>text</type>
    <notnull>true</notnull>
    <length>255</length>
   </field>
   <field>
    <name>trackback_excerpt</name>
    <type>clob</type>
    <notnull>true</notnull>
   </field>
   <field>
    <name>trackback_url</name>
    <type>text</type>
    <notnull>true</notnull>
    <length>255</length>
   </field>
   <field>
    <name>trackback_blog_name</name>
    <type>text</type>
    <notnull>true</notnull>
    <length>255</length>
   </field>
   <field>
    <name>trackback_node_id</name>
    <type>integer</type>
    <unsigned>true</unsigned>
    <notnull>false</notnull>
    <length>10</length>
   </field>
   <index>
    <name>PRIMARY</name>
    <primary>true</primary>
    <field>
     <name>trackback_id</name>
     <sorting>ascending</sorting>
    </field>
   </index>
   <index>
    <name>trackback_node</name>
    <field>
     <name>trackback_node_id</name>
    </field>
   </index>
  </declaration>
  <initialization>
  </initialization>
 </table>

 <table>
  <name>tag</name>
  <declaration>
   <field>
    <name>tag_id</name>
    <autoincrement>true</autoincrement>
    <type>integer</type>
    <unsigned>true</unsigned>
    <notnull>true</notnull>
    <length>10</length>
   </field>
   <field>
    <name>tag_created</name>
    <type>integer</type>
    <unsigned>true</unsigned>
    <notnull>true</notnull>
    <length>10</length>
   </field>
   <field>
    <name>tag_updated</name>
    <type>integer</type>
    <unsigned>true</unsigned>
    <notnull>true</notnull>
    <length>10</length>
   </field>
   <field>
    <name>tag_name</name>
    <type>text</type>
    <notnull>true</notnull>
    <length>255</length>
   </field>
   <index>
    <name>PRIMARY</name>
    <primary>true</primary>
    <field>
     <name>tag_id</name>
     <sorting>ascending</sorting>
    </field>
   </index>
   <index>
    <name>tag_name</name>
    <field>
     <name>tag_name</name>
     <length>20</length>
    </field>
   </index>
  </declaration>
  <initialization>
  </initialization>
 </table>

 <table>
  <name>vote</name>
  <declaration>
   <field>
    <name>vote_id</name>
    <autoincrement>true</autoincrement>
    <type>integer</type>
    <unsigned>true</unsigned>
    <notnull>true</notnull>
    <length>10</length>
   </field>
   <field>
    <name>vote_created</name>
    <type>integer</type>
    <unsigned>true</unsigned>
    <notnull>true</notnull>
    <length>10</length>
   </field>
   <field>
    <name>vote_updated</name>
    <type>integer</type>
    <unsigned>true</unsigned>
    <notnull>true</notnull>
    <length>10</length>
   </field>
   <field>
    <name>vote_score</name>
    <type>integer</type>
    <unsigned>true</unsigned>
    <notnull>true</notnull>
    <length>3</length>
   </field>
   <field>
    <name>vote_ip</name>
    <type>text</type>
    <notnull>true</notnull>
    <fixed>true</fixed>
    <length>15</length>
   </field>
   <field>
    <name>vote_node_id</name>
    <type>integer</type>
    <unsigned>true</unsigned>
    <notnull>false</notnull>
    <length>10</length>
   </field>
   <field>
    <name>vote_userid</name>
    <type>text</type>
    <notnull>true</notnull>
    <length>255</length>
   </field>
   <index>
    <name>PRIMARY</name>
    <primary>true</primary>
    <field>
     <name>vote_id</name>
     <sorting>ascending</sorting>
    </field>
   </index>
   <index>
    <name>vote_node</name>
    <field>
     <name>vote_node_id</name>
    </field>
   </index>
  </declaration>
  <initialization>
  </initialization>
 </table>

 <table>
  <name>plugin</name>
  <declaration>
   <field>
    <name>plugin_id</name>
    <autoincrement>true</autoincrement>
    <type>integer</type>
    <unsigned>true</unsigned>
    <notnull>true</notnull>
    <length>10</length>
   </field>
   <field>
    <name>plugin_created</name>
    <type>integer</type>
    <unsigned>true</unsigned>
    <notnull>true</notnull>
    <length>10</length>
   </field>
   <field>
    <name>plugin_updated</name>
    <type>integer</type>
    <unsigned>true</unsigned>
    <notnull>true</notnull>
    <length>10</length>
   </field>
   <field>
    <name>plugin_name</name>
    <type>text</type>
    <notnull>true</notnull>
    <length>255</length>
   </field>
   <field>
    <name>plugin_version</name>
    <type>text</type>
    <notnull>true</notnull>
    <length>15</length>
   </field>
   <field>
    <name>plugin_active</name>
    <type>integer</type>
    <unsigned>true</unsigned>
    <notnull>true</notnull>
    <length>1</length>
   </field>
   <field>
    <name>plugin_params</name>
    <type>clob</type>
    <notnull>true</notnull>
   </field>
   <field>
    <name>plugin_priority</name>
    <type>integer</type>
    <unsigned>true</unsigned>
    <notnull>true</notnull>
    <length>5</length>
   </field>
   <field>
    <name>plugin_locked</name>
    <type>integer</type>
    <unsigned>true</unsigned>
    <notnull>true</notnull>
    <length>1</length>
   </field>
   <index>
    <name>PRIMARY</name>
    <primary>true</primary>
    <field>
     <name>plugin_id</name>
     <sorting>ascending</sorting>
    </field>
   </index>
   <index>
    <name>plugin_name</name>
    <field>
     <name>plugin_name</name>
     <length>10</length>
    </field>
   </index>
  </declaration>
  <initialization>
  </initialization>
 </table>

 <table>
  <name>view</name>
  <declaration>
   <field>
    <name>view_id</name>
    <autoincrement>true</autoincrement>
    <type>integer</type>
    <unsigned>true</unsigned>
    <notnull>true</notnull>
    <length>10</length>
   </field>
   <field>
    <name>view_created</name>
    <type>integer</type>
    <unsigned>true</unsigned>
    <notnull>true</notnull>
    <length>10</length>
   </field>
   <field>
    <name>view_updated</name>
    <type>integer</type>
    <unsigned>true</unsigned>
    <notnull>true</notnull>
    <length>10</length>
   </field>
   <field>
    <name>view_uid</name>
    <type>text</type>
    <notnull>true</notnull>
    <length>255</length>
   </field>
   <field>
    <name>view_last</name>
    <type>integer</type>
    <unsigned>true</unsigned>
    <notnull>true</notnull>
    <length>10</length>
   </field>
   <field>
    <name>view_node_id</name>
    <type>integer</type>
    <unsigned>true</unsigned>
    <notnull>false</notnull>
    <length>10</length>
   </field>
   <index>
    <name>PRIMARY</name>
    <primary>true</primary>
    <field>
     <name>view_id</name>
     <sorting>ascending</sorting>
    </field>
   </index>
   <index>
    <name>view_uid</name>
    <field>
     <name>view_uid</name>
     <length>5</length>
    </field>
   </index>
  </declaration>
  <initialization>
  </initialization>
 </table>

 <table>
  <name>role</name>
  <declaration>
   <field>
    <name>role_id</name>
    <autoincrement>true</autoincrement>
    <type>integer</type>
    <unsigned>true</unsigned>
    <notnull>true</notnull>
    <length>10</length>
   </field>
   <field>
    <name>role_created</name>
    <type>integer</type>
    <unsigned>true</unsigned>
    <notnull>true</notnull>
    <length>10</length>
   </field>
   <field>
    <name>role_updated</name>
    <type>integer</type>
    <unsigned>true</unsigned>
    <notnull>true</notnull>
    <length>10</length>
   </field>
   <field>
    <name>role_name</name>
    <type>text</type>
    <notnull>true</notnull>
    <length>255</length>
   </field>
   <field>
    <name>role_permissions</name>
    <type>clob</type>
    <notnull>true</notnull>
   </field>
   <field>
    <name>role_system</name>
    <type>integer</type>
    <unsigned>true</unsigned>
    <notnull>true</notnull>
    <length>10</length>
   </field>
   <field>
    <name>role_member_count</name>
    <type>integer</type>
    <unsigned>true</unsigned>
    <notnull>true</notnull>
    <length>10</length>
   </field>
   <field>
    <name>role_member_last</name>
    <type>integer</type>
    <unsigned>true</unsigned>
    <notnull>true</notnull>
    <length>10</length>
   </field>
   <field>
    <name>role_member_lasttime</name>
    <type>integer</type>
    <unsigned>true</unsigned>
    <notnull>true</notnull>
    <length>10</length>
   </field>
   <index>
    <name>PRIMARY</name>
    <primary>true</primary>
    <field>
     <name>role_id</name>
     <sorting>ascending</sorting>
    </field>
   </index>
  </declaration>
 </table>

 <table>
  <name>member</name>
  <declaration>
   <field>
    <name>member_id</name>
    <autoincrement>true</autoincrement>
    <type>integer</type>
    <unsigned>true</unsigned>
    <notnull>true</notnull>
    <length>10</length>
   </field>
   <field>
    <name>member_created</name>
    <type>integer</type>
    <unsigned>true</unsigned>
    <notnull>true</notnull>
    <length>10</length>
   </field>
   <field>
    <name>member_updated</name>
    <type>integer</type>
    <unsigned>true</unsigned>
    <notnull>true</notnull>
    <length>10</length>
   </field>
   <field>
    <name>member_role_id</name>
    <type>integer</type>
    <unsigned>true</unsigned>
    <notnull>false</notnull>
    <length>10</length>
   </field>
   <field>
    <name>member_userid</name>
    <type>text</type>
    <notnull>true</notnull>
    <length>255</length>
   </field>
   <index>
    <name>PRIMARY</name>
    <primary>true</primary>
    <field>
     <name>member_id</name>
     <sorting>ascending</sorting>
    </field>
   </index>
   <index>
    <name>member_userid</name>
    <field>
     <name>member_userid</name>
     <length>5</length>
    </field>
   </index>
  </declaration>
  <initialization>
  </initialization>
 </table>

 <table>
  <name>node2tag</name>
  <declaration>
   <field>
    <name>node2tag_id</name>
    <autoincrement>true</autoincrement>
    <type>integer</type>
    <unsigned>true</unsigned>
    <notnull>true</notnull>
    <length>10</length>
   </field>
   <field>
    <name>node2tag_created</name>
    <type>integer</type>
    <unsigned>true</unsigned>
    <notnull>true</notnull>
    <length>10</length>
   </field>
   <field>
    <name>node2tag_updated</name>
    <type>integer</type>
    <unsigned>true</unsigned>
    <notnull>true</notnull>
    <length>10</length>
   </field>
   <field>
    <name>node2tag_node_id</name>
    <type>integer</type>
    <unsigned>true</unsigned>
    <notnull>false</notnull>
    <length>10</length>
   </field>
   <field>
    <name>node2tag_tag_id</name>
    <type>integer</type>
    <unsigned>true</unsigned>
    <notnull>false</notnull>
    <length>10</length>
   </field>
   <index>
    <name>PRIMARY</name>
    <primary>true</primary>
    <field>
     <name>node2tag_id</name>
     <sorting>ascending</sorting>
    </field>
   </index>
   <index>
    <name>node2tag_node</name>
    <field>
     <name>node2tag_node_id</name>
    </field>
   </index>
   <index>
    <name>node2tag_tag</name>
    <field>
     <name>node2tag_tag_id</name>
    </field>
   </index>
  </declaration>
  <initialization>
  </initialization>
 </table>

 <table>
  <name>category_tree</name>
  <declaration>
   <field>
    <name>tree_id</name>
    <type>integer</type>
    <unsigned>true</unsigned>
    <notnull>true</notnull>
    <length>10</length>
   </field>
   <field>
    <name>tree_left</name>
    <type>integer</type>
    <unsigned>true</unsigned>
    <notnull>true</notnull>
    <length>10</length>
   </field>
   <field>
    <name>tree_right</name>
    <type>integer</type>
    <unsigned>true</unsigned>
    <notnull>true</notnull>
    <length>10</length>
   </field>
  </declaration>
 </table>

 <table>
  <name>comment_tree</name>
  <declaration>
   <field>
    <name>tree_id</name>
    <type>integer</type>
    <unsigned>true</unsigned>
    <notnull>true</notnull>
    <length>10</length>
   </field>
   <field>
    <name>tree_left</name>
    <type>integer</type>
    <unsigned>true</unsigned>
    <notnull>true</notnull>
    <length>10</length>
   </field>
   <field>
    <name>tree_right</name>
    <type>integer</type>
    <unsigned>true</unsigned>
    <notnull>true</notnull>
    <length>10</length>
   </field>
  </declaration>
 </table>

</database>